cooptools/__init__.py
cooptools/anchor.py
cooptools/asyncable.py
cooptools/cnxn_info.py
cooptools/colors.py
cooptools/common.py
cooptools/config.py
cooptools/coopDataclass.py
cooptools/coopEnum.py
cooptools/coopthreading.py
cooptools/currency.py
cooptools/date_utils.py
cooptools/decay.py
cooptools/decor.py
cooptools/dictPolicies.py
cooptools/exceptions.py
cooptools/loggingHelpers.py
cooptools/marchingSquares.py
cooptools/matrixManipulation.py
cooptools/os_manip.py
cooptools/pandasHelpers.py
cooptools/plotting.py
cooptools/printing.py
cooptools/protocols.py
cooptools/randoms.py
cooptools/register.py
cooptools/retry.py
cooptools/timeWindow.py
cooptools/toggles.py
cooptools/transform.py
cooptools/trends.py
cooptools/typeProviders.py
cooptools/typevalidation.py
cooptools/version.py
cooptools/cli/CliAtomicUserInteraction.py
cooptools/cli/CliMenu.py
cooptools/cli/__init__.py
cooptools/cli/fileContentReturn.py
cooptools/commandDesignPattern/__init__.py
cooptools/commandDesignPattern/commandController.py
cooptools/commandDesignPattern/commandProtocol.py
cooptools/commandDesignPattern/exceptions.py
cooptools/dataRefresher/__init__.py
cooptools/dataRefresher/dataHub.py
cooptools/dataRefresher/dataRefresher.py
cooptools/dataStore/__init__.py
cooptools/dataStore/dataProcessor.py
cooptools/dataStore/dataStoreProtocol.py
cooptools/dataStore/dbConnectionURI.py
cooptools/dataStore/inMemoryDataStore.py
cooptools/expertise/__init__.py
cooptools/expertise/expertiseArgs.py
cooptools/expertise/expertiseSchedules.py
cooptools/finance/__init__.py
cooptools/finance/dicounted_cashflow_analysis.py
cooptools/finance/futureValueProjector.py
cooptools/finance/growth_projections.py
cooptools/finance/reports.py
cooptools/finance/utils.py
cooptools/geometry_utils/__init__.py
cooptools/geometry_utils/circle_utils.py
cooptools/geometry_utils/common.py
cooptools/geometry_utils/curve_utils.py
cooptools/geometry_utils/line_utils.py
cooptools/geometry_utils/polygon_utils.py
cooptools-1.49.dist-info/METADATA
cooptools-1.49.dist-info/WHEEL
cooptools-1.49.dist-info/top_level.txt
cooptools-1.49.dist-info/RECORD
